LICENSE
MANIFEST.in
kindlestrip.py
setup.py
yakindlestrip.egg-info/PKG-INFO
yakindlestrip.egg-info/SOURCES.txt
yakindlestrip.egg-info/dependency_links.txt
yakindlestrip.egg-info/top_level.txt