Metadata-Version: 1.1
Name: yakindlestrip
Version: 1.36
Summary: yet another pip-installable conversion of Paul Durrant's kindlestrip
Home-page: https://github.com/fireinice/yakindlestrip
Author: Zigler Zhang
Author-email: zigler.zhang@gmail.com
License: The MIT License (MIT)
